httpopen/__init__.py
httpopen/sync.py
httpopen-0.1.1.dist-info/LICENSE
httpopen-0.1.1.dist-info/METADATA
httpopen-0.1.1.dist-info/WHEEL
httpopen-0.1.1.dist-info/top_level.txt
httpopen-0.1.1.dist-info/RECORD
