Metadata-Version: 2.1
Name: httpopen
Version: 0.1.1
License-File: LICENSE
Requires-Dist: requests
